README.rst
setup.py
resyndicator/__init__.py
resyndicator/console.py
resyndicator/models.py
resyndicator/resyndicators.py
resyndicator/services.py
resyndicator/settings.py
resyndicator.egg-info/PKG-INFO
resyndicator.egg-info/SOURCES.txt
resyndicator.egg-info/dependency_links.txt
resyndicator.egg-info/entry_points.txt
resyndicator.egg-info/not-zip-safe
resyndicator.egg-info/requires.txt
resyndicator.egg-info/top_level.txt
resyndicator/fetchers/__init__.py
resyndicator/fetchers/base.py
resyndicator/fetchers/content.py
resyndicator/fetchers/feed.py
resyndicator/fetchers/sitemap.py
resyndicator/fetchers/twitter.py
resyndicator/tests/__init__.py
resyndicator/tests/conftest.py
resyndicator/tests/test_feed_fetcher.py
resyndicator/tests/test_resyndicators.py
resyndicator/tests/test_sitemap_fetcher.py
resyndicator/tests/test_sitemapparser.py
resyndicator/tests/test_utils.py
resyndicator/utils/__init__.py
resyndicator/utils/clustering.py
resyndicator/utils/finder.py
resyndicator/utils/logger.py
resyndicator/utils/sitemapparser.py
resyndicator/utils/utils.py