Metadata-Version: 1.1
Name: resyndicator
Version: 0.8.0
Summary: Aggregates data from many sources into merged and filtered Atom feeds.
Home-page: https://bitbucket.org/Telofy/resyndicator
Author: Denis Drescher
Author-email: denis.drescher+resyndicator@claviger.net
License: Apache 2.0
Platform: UNKNOWN
Classifier: Development Status :: 4 - Beta
Classifier: Intended Audience :: Developers
Classifier: Natural Language :: English
Classifier: License :: OSI Approved :: Apache Software License
Classifier: Programming Language :: Python
Classifier: Programming Language :: Python :: 3
Classifier: Programming Language :: Python :: 3.4
Classifier: Programming Language :: Python :: 3.5
Classifier: Programming Language :: Python :: 3.6
Classifier: Programming Language :: Python :: Implementation :: CPython
